otter_submit/_version.py
otter_submit-0.1.11.data/data/share/jupyter/labextensions/@otter-submit/submit-button/install.json
otter_submit-0.1.11.dist-info/METADATA
otter_submit-0.1.11.dist-info/WHEEL
otter_submit-0.1.11.dist-info/licenses/LICENSE
otter_submit-0.1.11.dist-info/RECORD
